framalytics/FRAM_Visualizer.py
framalytics/__init__.py
framalytics/fram.py
framalytics/xfmv_parser.py
framalytics/tests/__init__.py
framalytics/tests/test_fram.py
framalytics/tests/test_xfmv_parser.py
framalytics/tests/resources/simple_fram.xfmv
framalytics-1.0.0.dist-info/LICENSE
framalytics-1.0.0.dist-info/WHEEL
framalytics-1.0.0.dist-info/METADATA
framalytics-1.0.0.dist-info/RECORD
