Metadata-Version: 2.1
Name: framalytics
Version: 1.0.0
Summary: Python tools for the Function Resonance Analysis Method
Author-email: "Terrence S. Tricco" <tstricco@mun.ca>
Classifier: License :: OSI Approved :: GNU General Public License v3 or later (GPLv3+)
Classifier: Intended Audience :: Science/Research
Project-URL: Docs, https://framalytics.readthedocs.io
Project-URL: Source, https://github.com/ttricco/framalytics
